README.md
setup.py
rsensor/__init__.py
rsensor/data/rsensor.service
rsensor/data/schema.yml
rsensor/data/test_node.yml
rsensor/database/__init__.py
rsensor/database/db.py
rsensor/database/dbbase.py
rsensor/database/dbmysql.py
rsensor/database/dbsqlite.py
rsensor/database/init_db.py
rsensor/database/mqtt_to_db.py
rsensor/logger/__init__.py
rsensor/logger/rsensor_logger.py
rsensor/testapp/__init__.py
rsensor/testapp/rsensor_testgen.py
rsensor/testapp/wipemqtt.py
rsensor/webapp/__init__.py
rsensor/webapp/main.py
test/test_dbbase.py
test/test_dbsqlite.py
test/test_rsensor_schema.py
uracoli_rsensor.egg-info/PKG-INFO
uracoli_rsensor.egg-info/SOURCES.txt
uracoli_rsensor.egg-info/dependency_links.txt
uracoli_rsensor.egg-info/entry_points.txt
uracoli_rsensor.egg-info/requires.txt
uracoli_rsensor.egg-info/top_level.txt