Metadata-Version: 2.1
Name: uracoli-rsensor
Version: 0.1.2
Summary: A sensor logger framework for the uracoli rsensor firmware
Home-page: UNKNOWN
Maintainer: Axel Wachtler
Maintainer-email: axel@uracoli.de
License: BSD
Platform: UNKNOWN
